lameenc.cpython-310-aarch64-linux-gnu.so
lameenc-1.8.1.dist-info/top_level.txt
lameenc-1.8.1.dist-info/RECORD
lameenc-1.8.1.dist-info/LICENSE
lameenc-1.8.1.dist-info/METADATA
lameenc-1.8.1.dist-info/WHEEL
