Metadata-Version: 2.1
Name: lameenc
Version: 1.8.1
Summary: LAME encoding bindings
Home-page: https://github.com/chrisstaite/lameenc
Author: Chris Staite
Author-email: Chris Staite <chris@yourdreamnet.co.uk>
License: GNU LESSER GENERAL PUBLIC LICENSE
Project-URL: Repository, https://github.com/chrisstaite/lameenc
Classifier: Topic :: Multimedia :: Sound/Audio :: Conversion
Classifier: Programming Language :: Python :: 3 :: Only
Classifier: License :: OSI Approved :: GNU Lesser General Public License v3 (LGPLv3)
Classifier: Operating System :: MacOS :: MacOS X
Classifier: Operating System :: Microsoft :: Windows
Classifier: Operating System :: POSIX :: Linux
License-File: LICENSE
